<?xml version="1.0" encoding="UTF-8"?>
<metadata>
	<add-node
		path="/api/package[@name='com.facebook.stetho.inspector.elements']/class[@name='Descriptor']">
		<method
			abstract="true"
			deprecated="not deprecated"
			final="false"
			name="getAttributes"
			native="false"
			return="void"
			static="false"
			synchronized="false"
			visibility="public">
			<parameter
				name="p0"
				type="java.lang.Object">
			</parameter>
			<parameter
				name="p1"
				type="com.facebook.stetho.inspector.elements.AttributeAccumulator">
			</parameter>
		</method>
		<method
			abstract="true"
			deprecated="not deprecated"
			final="false"
			name="getChildren"
			native="false"
			return="void"
			static="false"
			synchronized="false"
			visibility="public">
			<parameter
				name="p0"
				type="java.lang.Object">
			</parameter>
			<parameter
				name="p1"
				type="com.facebook.stetho.common.Accumulator&lt;java.lang.Object&gt;">
			</parameter>
		</method>
		<method
			abstract="true"
			deprecated="not deprecated"
			final="false"
			name="getComputedStyles"
			native="false"
			return="void"
			static="false"
			synchronized="false"
			visibility="public">
			<parameter
				name="p0"
				type="E">
			</parameter>
			<parameter
				name="p1"
				type="com.facebook.stetho.inspector.elements.ComputedStyleAccumulator">
			</parameter>
		</method>
		<method
			abstract="true"
			deprecated="not deprecated"
			final="false"
			name="getLocalName"
			native="false"
			return="java.lang.String"
			static="false"
			synchronized="false"
			visibility="public">
			<parameter
				name="p0"
				type="java.lang.Object">
			</parameter>
		</method>
		<method
			abstract="true"
			deprecated="not deprecated"
			final="false"
			name="getNodeName"
			native="false"
			return="java.lang.String"
			static="false"
			synchronized="false"
			visibility="public">
			<parameter
				name="p0"
				type="java.lang.Object">
			</parameter>
		</method>
		<method
			abstract="true"
			deprecated="not deprecated"
			final="false"
			name="getNodeType"
			native="false"
			return="com.facebook.stetho.inspector.elements.NodeType"
			static="false"
			synchronized="false"
			visibility="public">
			<parameter
				name="p0"
				type="java.lang.Object">
			</parameter>
		</method>
		<method
			abstract="true"
			deprecated="not deprecated"
			final="false"
			name="getNodeValue"
			native="false"
			return="java.lang.String"
			static="false"
			synchronized="false"
			visibility="public">
			<parameter
				name="p0"
				type="E">
			</parameter>
		</method>
		<method
			abstract="true"
			deprecated="not deprecated"
			final="false"
			name="getStyleRuleNames"
			native="false"
			return="void"
			static="false"
			synchronized="false"
			visibility="public">
			<parameter
				name="p0"
				type="E">
			</parameter>
			<parameter
				name="p1"
				type="com.facebook.stetho.inspector.elements.StyleRuleNameAccumulator">
			</parameter>
		</method>
		<method
			abstract="true"
			deprecated="not deprecated"
			final="false"
			name="getStyles"
			native="false"
			return="void"
			static="false"
			synchronized="false"
			visibility="public">
			<parameter
				name="p0"
				type="E">
			</parameter>
			<parameter
				name="p1"
				type="java.lang.String">
			</parameter>
			<parameter
				name="p2"
				type="com.facebook.stetho.inspector.elements.StyleAccumulator">
			</parameter>
		</method>
		<method
			abstract="true"
			deprecated="not deprecated"
			final="false"
			name="hook"
			native="false"
			return="void"
			static="false"
			synchronized="false"
			visibility="public">
			<parameter
				name="p0"
				type="java.lang.Object">
			</parameter>
		</method>
		<method
			abstract="true"
			deprecated="not deprecated"
			final="false"
			name="setAttributesAsText"
			native="false"
			return="void"
			static="false"
			synchronized="false"
			visibility="public">
			<parameter
				name="p0"
				type="java.lang.Object">
			</parameter>
			<parameter
				name="p1"
				type="java.lang.String">
			</parameter>
		</method>
		<method
			abstract="true"
			deprecated="not deprecated"
			final="false"
			name="setStyle"
			native="false"
			return="void"
			static="false"
			synchronized="false"
			visibility="public">
			<parameter
				name="p0"
				type="E">
			</parameter>
			<parameter
				name="p1"
				type="java.lang.String">
			</parameter>
			<parameter
				name="p2"
				type="java.lang.String">
			</parameter>
			<parameter
				name="p3"
				type="java.lang.String">
			</parameter>
		</method>
		<method
			abstract="true"
			deprecated="not deprecated"
			final="false"
			name="unhook"
			native="false"
			return="void"
			static="false"
			synchronized="false"
			visibility="public">
			<parameter
				name="p0"
				type="java.lang.Object">
			</parameter>
		</method>
	</add-node>
	<attr
		path="/api/package[@name='com.facebook.stetho.inspector.database']/class[@name='ContentProviderDatabaseDriver']/method[@name='getDatabaseNames' and count(parameter)=0]"
		name="managedReturn">System.Collections.IList</attr>
	<attr
		path="/api/package[@name='com.facebook.stetho.inspector.database']/class[@name='DatabaseDriver2Adapter']/method[@name='getDatabaseNames' and count(parameter)=0]"
		name="managedReturn">System.Collections.IList</attr>
	<attr
		path="/api/package[@name='com.facebook.stetho.inspector.database']/class[@name='SqliteDatabaseDriver']/method[@name='getDatabaseNames' and count(parameter)=0]"
		name="managedReturn">System.Collections.IList</attr>
	<attr
		path="/api/package[@name='com.facebook.stetho.inspector.network']/class[@name='CountingOutputStream']"
		name="visibility">public</attr>
	<attr
		path="/api/package[@name='com.facebook.stetho.inspector.database']/class[@name='ContentProviderDatabaseDriver.ContentProviderDatabaseDescriptor']"
		name="visibility">public</attr>
	<remove-node
		path="/api/package[@name='com.facebook.stetho.inspector.database']/class[@name='ContentProviderDatabaseDriver']" />
	<remove-node
		path="/api/package[@name='com.facebook.stetho.inspector.database']/class[@name='DatabaseDriver2Adapter']" />
	<remove-node
		path="/api/package[@name='com.facebook.stetho.inspector.database']/class[@name='SqliteDatabaseDriver']" />
	<add-node
		path="/api/package[@name='com.facebook.stetho.inspector.database']">
		<class
			abstract="false"
			deprecated="not deprecated"
			extends="com.facebook.stetho.inspector.protocol.module.DatabaseDriver2"
			extends-generic-aware="com.facebook.stetho.inspector.protocol.module.DatabaseDriver2&lt;com.facebook.stetho.inspector.database.ContentProviderDatabaseDriver.ContentProviderDatabaseDescriptor&gt;"
			final="false"
			name="ContentProviderDatabaseDriver"
			static="false"
			visibility="public">
			<constructor
				deprecated="not deprecated"
				final="false"
				name="ContentProviderDatabaseDriver"
				static="false"
				type="com.facebook.stetho.inspector.database.ContentProviderDatabaseDriver"
				visibility="public">
				<parameter
					name="p0"
					type="android.content.Context">
				</parameter>
				<parameter
					name="p1"
					type="com.facebook.stetho.inspector.database.ContentProviderSchema...">
				</parameter>
			</constructor>
			<method
				abstract="false"
				deprecated="not deprecated"
				final="false"
				name="getDatabaseNames"
				native="false"
				return="java.util.List"
				static="false"
				synchronized="false"
				visibility="public">
			</method>
			<method
				abstract="false"
				deprecated="not deprecated"
				final="false"
				name="executeSQL"
				native="false"
				return="com.facebook.stetho.inspector.protocol.module.Database.ExecuteSQLResponse"
				static="false"
				synchronized="false"
				visibility="public">
				<parameter
					name="p0"
					type="java.lang.String">
				</parameter>
				<parameter
					name="p1"
					type="java.lang.String">
				</parameter>
				<parameter
					name="p2"
					type="com.facebook.stetho.inspector.protocol.module.BaseDatabaseDriver.ExecuteResultHandler&lt;com.facebook.stetho.inspector.protocol.module.Database.ExecuteSQLResponse&gt;">
				</parameter>
				<exception
					name="SQLiteException"
					type="android.database.sqlite.SQLiteException">
				</exception>
			</method>
			<method
				abstract="false"
				deprecated="not deprecated"
				final="false"
				name="getTableNames"
				native="false"
				return="java.util.List&lt;java.lang.String&gt;"
				static="false"
				synchronized="false"
				visibility="public">
				<parameter
					name="p0"
					type="java.lang.String">
				</parameter>
			</method>
		</class>
		<class
			abstract="false"
			deprecated="deprecated"
			extends="com.facebook.stetho.inspector.protocol.module.DatabaseDriver2"
			extends-generic-aware="com.facebook.stetho.inspector.protocol.module.DatabaseDriver2&lt;com.facebook.stetho.inspector.database.DatabaseDriver2Adapter.StringDatabaseDescriptor&gt;"
			final="false"
			name="DatabaseDriver2Adapter"
			static="false"
			visibility="public">
			<constructor
				deprecated="not deprecated"
				final="false"
				name="DatabaseDriver2Adapter"
				static="false"
				type="com.facebook.stetho.inspector.database.DatabaseDriver2Adapter"
				visibility="public">
				<parameter
					name="p0"
					type="com.facebook.stetho.inspector.protocol.module.Database.DatabaseDriver">
				</parameter>
			</constructor>
			<method
				abstract="false"
				deprecated="not deprecated"
				final="false"
				name="getDatabaseNames"
				native="false"
                return="java.util.List"
				static="false"
				synchronized="false"
				visibility="public">
			</method>
			<method
				abstract="false"
				deprecated="not deprecated"
				final="false"
				name="executeSQL"
				native="false"
				return="com.facebook.stetho.inspector.protocol.module.Database.ExecuteSQLResponse"
				static="false"
				synchronized="false"
				visibility="public">
				<parameter
					name="p0"
					type="java.lang.String">
				</parameter>
				<parameter
					name="p1"
					type="java.lang.String">
				</parameter>
				<parameter
					name="p2"
					type="com.facebook.stetho.inspector.protocol.module.BaseDatabaseDriver.ExecuteResultHandler&lt;com.facebook.stetho.inspector.protocol.module.Database.ExecuteSQLResponse&gt;">
				</parameter>
				<exception
					name="SQLiteException"
					type="android.database.sqlite.SQLiteException">
				</exception>
			</method>
			<method
				abstract="false"
				deprecated="not deprecated"
				final="false"
				name="getTableNames"
				native="false"
				return="java.util.List&lt;java.lang.String&gt;"
				static="false"
				synchronized="false"
				visibility="public">
				<parameter
					name="p0"
					type="java.lang.String">
				</parameter>
			</method>
		</class>
		<class
			abstract="false"
			deprecated="not deprecated"
			extends="com.facebook.stetho.inspector.protocol.module.DatabaseDriver2"
			extends-generic-aware="com.facebook.stetho.inspector.protocol.module.DatabaseDriver2&lt;com.facebook.stetho.inspector.database.SqliteDatabaseDriver.SqliteDatabaseDescriptor&gt;"
			final="false"
			name="SqliteDatabaseDriver"
			static="false"
			visibility="public">
			<constructor
				deprecated="not deprecated"
				final="false"
				name="SqliteDatabaseDriver"
				static="false"
				type="com.facebook.stetho.inspector.database.SqliteDatabaseDriver"
				visibility="public">
				<parameter
					name="p0"
					type="android.content.Context">
				</parameter>
				<parameter
					name="p1"
					type="com.facebook.stetho.inspector.database.DatabaseFilesProvider">
				</parameter>
				<parameter
					name="p2"
					type="com.facebook.stetho.inspector.database.DatabaseConnectionProvider">
				</parameter>
			</constructor>
			<constructor
				deprecated="deprecated"
				final="false"
				name="SqliteDatabaseDriver"
				static="false"
				type="com.facebook.stetho.inspector.database.SqliteDatabaseDriver"
				visibility="public">
				<parameter
					name="p0"
					type="android.content.Context">
				</parameter>
				<parameter
					name="p1"
					type="com.facebook.stetho.inspector.database.DatabaseFilesProvider">
				</parameter>
			</constructor>
			<constructor
				deprecated="deprecated"
				final="false"
				name="SqliteDatabaseDriver"
				static="false"
				type="com.facebook.stetho.inspector.database.SqliteDatabaseDriver"
				visibility="public">
				<parameter
					name="p0"
					type="android.content.Context">
				</parameter>
			</constructor>
			<method
				abstract="false"
				deprecated="not deprecated"
				final="false"
				name="getDatabaseNames"
				native="false"
                return="java.util.List"
				static="false"
				synchronized="false"
				visibility="public">
			</method>
			<method
				abstract="false"
				deprecated="not deprecated"
				final="false"
				name="executeSQL"
				native="false"
				return="com.facebook.stetho.inspector.protocol.module.Database.ExecuteSQLResponse"
				static="false"
				synchronized="false"
				visibility="public">
				<parameter
					name="p0"
					type="java.lang.String">
				</parameter>
				<parameter
					name="p1"
					type="java.lang.String">
				</parameter>
				<parameter
					name="p2"
					type="com.facebook.stetho.inspector.protocol.module.BaseDatabaseDriver.ExecuteResultHandler&lt;com.facebook.stetho.inspector.protocol.module.Database.ExecuteSQLResponse&gt;">
				</parameter>
				<exception
					name="SQLiteException"
					type="android.database.sqlite.SQLiteException">
				</exception>
			</method>
			<method
				abstract="false"
				deprecated="not deprecated"
				final="false"
				name="getTableNames"
				native="false"
				return="java.util.List&lt;java.lang.String&gt;"
				static="false"
				synchronized="false"
				visibility="public">
				<parameter
					name="p0"
					type="java.lang.String">
				</parameter>
			</method>
		</class>
	</add-node>
</metadata>